Metadata-Version: 2.1
Name: unicontract
Version: 0.2.1
License: Apache-2.0
Classifier: Programming Language :: Python :: 3
Classifier: License :: OSI Approved :: Apache Software License
Classifier: Operating System :: OS Independent
License-File: LICENSE
Requires-Dist: antlr4-python3-runtime==4.13.2
Requires-Dist: jsondiff>=2.2.1
Requires-Dist: PyYAML>=6.0.2
Requires-Dist: argparse>=1.4.0
Requires-Dist: clr-loader>=0.2.6
Requires-Dist: pythonnet>=3.0.4
Requires-Dist: setuptools>=75.6.0
